autl/Recorder.py
autl/__init__.py
autl/ppa_util.py
fk_aaronhu-0.0.12.dist-info/METADATA
fk_aaronhu-0.0.12.dist-info/WHEEL
fk_aaronhu-0.0.12.dist-info/licenses/LICENSE
fk_aaronhu-0.0.12.dist-info/RECORD
